kraken_aliyun_api_gateway_sdk/ClientDemo.py
kraken_aliyun_api_gateway_sdk/__init__.py
kraken_aliyun_api_gateway_sdk/com/__init__.py
kraken_aliyun_api_gateway_sdk/com/aliyun/__init__.py
kraken_aliyun_api_gateway_sdk/com/aliyun/api/__init__.py
kraken_aliyun_api_gateway_sdk/com/aliyun/api/gateway/__init__.py
kraken_aliyun_api_gateway_sdk/com/aliyun/api/gateway/sdk/__init__.py
kraken_aliyun_api_gateway_sdk/com/aliyun/api/gateway/sdk/client.py
kraken_aliyun_api_gateway_sdk/com/aliyun/api/gateway/sdk/auth/__init__.py
kraken_aliyun_api_gateway_sdk/com/aliyun/api/gateway/sdk/auth/md5_tool.py
kraken_aliyun_api_gateway_sdk/com/aliyun/api/gateway/sdk/auth/sha_hmac256.py
kraken_aliyun_api_gateway_sdk/com/aliyun/api/gateway/sdk/auth/signature_composer.py
kraken_aliyun_api_gateway_sdk/com/aliyun/api/gateway/sdk/auth/url_encoder.py
kraken_aliyun_api_gateway_sdk/com/aliyun/api/gateway/sdk/common/__init__.py
kraken_aliyun_api_gateway_sdk/com/aliyun/api/gateway/sdk/common/constant.py
kraken_aliyun_api_gateway_sdk/com/aliyun/api/gateway/sdk/http/__init__.py
kraken_aliyun_api_gateway_sdk/com/aliyun/api/gateway/sdk/http/request.py
kraken_aliyun_api_gateway_sdk/com/aliyun/api/gateway/sdk/http/response.py
kraken_aliyun_api_gateway_sdk/com/aliyun/api/gateway/sdk/util/DateUtil.py
kraken_aliyun_api_gateway_sdk/com/aliyun/api/gateway/sdk/util/ParamUtil.py
kraken_aliyun_api_gateway_sdk/com/aliyun/api/gateway/sdk/util/UUIDUtil.py
kraken_aliyun_api_gateway_sdk/com/aliyun/api/gateway/sdk/util/__init__.py
kraken_aliyun_api_gateway_sdk-2021.9.7.1631008181.dist-info/METADATA
kraken_aliyun_api_gateway_sdk-2021.9.7.1631008181.dist-info/WHEEL
kraken_aliyun_api_gateway_sdk-2021.9.7.1631008181.dist-info/top_level.txt
kraken_aliyun_api_gateway_sdk-2021.9.7.1631008181.dist-info/RECORD
